punic/__init__.py
punic/cartfile.py
punic/carthage_cache.py
punic/checkout.py
punic/config.py
punic/config_init.py
punic/copy_frameworks.py
punic/errors.py
punic/github.py
punic/graph.py
punic/logger.py
punic/platform.py
punic/punic_cli.py
punic/repository.py
punic/resolver.py
punic/runner.py
punic/search.py
punic/semantic_version.py
punic/shshutil.py
punic/specification.py
punic/styling.py
punic/utilities.py
punic/version_check.py
punic/xcode.py
punic-0.2.10.dist-info/DESCRIPTION.rst
punic-0.2.10.dist-info/METADATA
punic-0.2.10.dist-info/RECORD
punic-0.2.10.dist-info/WHEEL
punic-0.2.10.dist-info/entry_points.txt
punic-0.2.10.dist-info/metadata.json
punic-0.2.10.dist-info/top_level.txt
