Metadata-Version: 2.0
Name: punic
Version: 0.2.10
Summary: Clean room python implementation of a subset of Carthage functionality
Home-page: http://github.com/schwa/punic
Author: Jonathan Wight
Author-email: jwight@mac.com
License: MIT
Keywords: carthage,build,xcode,iOS,cocoapods,cocoa,macOS
Platform: UNKNOWN
Classifier: Development Status :: 4 - Beta
Classifier: Environment :: MacOS X
Classifier: Intended Audience :: Developers
Classifier: License :: OSI Approved :: MIT License
Classifier: Operating System :: MacOS :: MacOS X
Classifier: Programming Language :: Python :: 2.7
Classifier: Programming Language :: Python :: 3.6
Classifier: Topic :: Software Development :: Build Tools
Requires-Dist: affirm
Requires-Dist: blessings
Requires-Dist: boto
Requires-Dist: click
Requires-Dist: click-didyoumean
Requires-Dist: flufl.enum
Requires-Dist: jsonpath-rw
Requires-Dist: memoize
Requires-Dist: networkx
Requires-Dist: pathlib2
Requires-Dist: prompt-toolkit
Requires-Dist: pyyaml
Requires-Dist: requests
Requires-Dist: six
Requires-Dist: tqdm
